{
  "type": "create:mixing",
  "ingredients": [
    {
      "tag": "forge:nuggets/zinc"
    },
    {
      "tag": "forge:nuggets/zinc"
    },
    {
      "tag": "forge:nuggets/iron"
    },
    {
      "tag": "forge:nuggets/iron"
    },
    {
      "item": "minecraft:dragon_breath"
    },
    {
      "item": "minecraft:popped_chorus_fruit"
    },
    {
      "item": "minecraft:popped_chorus_fruit"
    },
    {
      "item": "minecraft:popped_chorus_fruit"
    },
    {
      "item": "minecraft:popped_chorus_fruit"
    }
  ],
  "results": [
    {
      "item": "rainbowcompound:chorusite_ingot"
    }
  ],
  "heatRequirement": "heated"
}